callmefair/__init__.py
callmefair/mitigation/__init__.py
callmefair/mitigation/fair_bm.py
callmefair/mitigation/fair_grid.py
callmefair/mitigation/fair_log.py
callmefair/search/__init__.py
callmefair/search/_search_base.py
callmefair/search/fair_search.py
callmefair/util/__init__.py
callmefair/util/fair_util.py
callmefair-0.0.4.dist-info/METADATA
callmefair-0.0.4.dist-info/WHEEL
callmefair-0.0.4.dist-info/licenses/LICENSE
callmefair-0.0.4.dist-info/RECORD
