Metadata-Version: 2.4
Name: callmefair
Version: 0.0.4
Summary: A comprehensive framework for automatic bias mitigation in AI systems
Project-URL: Homepage, https://github.com/uofc-ai2lab/callmefair/
Project-URL: Issues, https://github.com/uofc-ai2lab/callmefair/issues
Author-email: Pedro Paiva <pedro.paiva1@ucalgary.ca>
License-Expression: MIT
License-File: LICENSE
Classifier: Operating System :: OS Independent
Classifier: Programming Language :: Python :: 3
Requires-Python: >=3.11
